rospy2/__init__.py
rospy2/constants.py
rospy2-1.0.3.dist-info/LICENSE
rospy2-1.0.3.dist-info/METADATA
rospy2-1.0.3.dist-info/WHEEL
rospy2-1.0.3.dist-info/top_level.txt
rospy2-1.0.3.dist-info/RECORD
